hbindpy/__init__.py
hbindpy/__main__.py
hbindpy/data/hbindpy.py
hbindpy/data/print.py
hbindpy/data/setup_engine.py
hbindpy/data/setup_engine.pyi
hbindpy/data/utils.py
hbindpy/data/version.py
hbindpy/data/__pycache__/hbindpy.cpython-311.pyc
hbindpy/data/__pycache__/print.cpython-311.pyc
hbindpy/data/__pycache__/setup_engine.cpython-311.pyc
hbindpy/data/__pycache__/utils.cpython-311.pyc
hbindpy/data/__pycache__/version.cpython-311.pyc
hbindpy/data/_image/icon.ico
hbindpy-1.1.dist-info/licenses/LICENSE.txt
hbindpy-1.1.dist-info/METADATA
hbindpy-1.1.dist-info/WHEEL
hbindpy-1.1.dist-info/entry_points.txt
hbindpy-1.1.dist-info/top_level.txt
hbindpy-1.1.dist-info/RECORD
