Metadata-Version: 2.4
Name: hbindpy
Version: 1.1
Summary: hbindpy
Author: huang yi yi
Author-email: 363766687@qq.com
Classifier: Programming Language :: Python :: 3
Classifier: License :: OSI Approved :: MIT License
Classifier: Operating System :: OS Independent
Requires-Python: >=3.7
License-File: LICENSE.txt
Requires-Dist: colorama
Requires-Dist: pyinstaller; platform_system == "Windows"
Dynamic: author
Dynamic: author-email
Dynamic: classifier
Dynamic: license-file
Dynamic: requires-dist
Dynamic: requires-python
Dynamic: summary
